AHP/__init__.py
AHP/ahp.py
AHP-0.0.1.dist-info/METADATA
AHP-0.0.1.dist-info/WHEEL
AHP-0.0.1.dist-info/top_level.txt
AHP-0.0.1.dist-info/RECORD
